es_configly/__init__.py
es_configly/configly.py
es_configly-0.0.13.dist-info/LICENSE
es_configly-0.0.13.dist-info/METADATA
es_configly-0.0.13.dist-info/WHEEL
es_configly-0.0.13.dist-info/top_level.txt
es_configly-0.0.13.dist-info/RECORD
